docs/source/conf.py
ivoryos/__init__.py
ivoryos/app.py
ivoryos/config.py
ivoryos/server.py
ivoryos/socket_handlers.py
ivoryos/version.py
ivoryos/optimizer/ax_optimizer.py
ivoryos/optimizer/base_optimizer.py
ivoryos/optimizer/baybe_optimizer.py
ivoryos/optimizer/nimo_optimizer.py
ivoryos/optimizer/registry.py
ivoryos/routes/__init__.py
ivoryos/routes/auth/__init__.py
ivoryos/routes/auth/auth.py
ivoryos/routes/auth/templates/change_password.html
ivoryos/routes/auth/templates/login.html
ivoryos/routes/auth/templates/signup.html
ivoryos/routes/control/__init__.py
ivoryos/routes/control/control.py
ivoryos/routes/control/control_file.py
ivoryos/routes/control/control_new_device.py
ivoryos/routes/control/utils.py
ivoryos/routes/control/templates/controllers.html
ivoryos/routes/control/templates/controllers_new.html
ivoryos/routes/data/__init__.py
ivoryos/routes/data/data.py
ivoryos/routes/data/templates/workflow_database.html
ivoryos/routes/data/templates/workflow_view.html
ivoryos/routes/data/templates/components/step_card.html
ivoryos/routes/design/__init__.py
ivoryos/routes/design/design.py
ivoryos/routes/design/design_file.py
ivoryos/routes/design/design_step.py
ivoryos/routes/design/templates/experiment_builder.html
ivoryos/routes/design/templates/components/action_form.html
ivoryos/routes/design/templates/components/actions_panel.html
ivoryos/routes/design/templates/components/autofill_toggle.html
ivoryos/routes/design/templates/components/canvas.html
ivoryos/routes/design/templates/components/canvas_footer.html
ivoryos/routes/design/templates/components/canvas_header.html
ivoryos/routes/design/templates/components/canvas_main.html
ivoryos/routes/design/templates/components/deck_selector.html
ivoryos/routes/design/templates/components/edit_action_form.html
ivoryos/routes/design/templates/components/info_modal.html
ivoryos/routes/design/templates/components/instruments_panel.html
ivoryos/routes/design/templates/components/modals.html
ivoryos-1.5.12.dist-info/licenses/LICENSE
ivoryos-1.5.12.dist-info/METADATA
ivoryos-1.5.12.dist-info/WHEEL
ivoryos-1.5.12.dist-info/top_level.txt
ivoryos-1.5.12.dist-info/RECORD
