Metadata-Version: 2.4
Name: ivoryos
Version: 1.5.12
Summary: an open-source Python package enabling Self-Driving Labs (SDLs) interoperability
Author-email: Ivory Zhang <ivoryzhang@chem.ubc.ca>
License: MIT
Project-URL: Homepage, https://gitlab.com/heingroup/ivoryos
Requires-Python: >=3.7
License-File: LICENSE
Requires-Dist: bcrypt
Requires-Dist: Flask[async]
Requires-Dist: Flask-Login
Requires-Dist: Flask-Session
Requires-Dist: Flask-SocketIO
Requires-Dist: Flask-SQLAlchemy
Requires-Dist: Flask-WTF
Requires-Dist: SQLAlchemy-Utils
Requires-Dist: python-dotenv
Requires-Dist: pandas
Requires-Dist: astor; python_version < "3.9"
Provides-Extra: optimizer-ax
Requires-Dist: ax-platform; extra == "optimizer-ax"
Provides-Extra: optimizer-baybe
Requires-Dist: baybe; extra == "optimizer-baybe"
Provides-Extra: optimizer-nimo
Requires-Dist: nimo; extra == "optimizer-nimo"
Provides-Extra: db
Requires-Dist: psycopg2-binary; extra == "db"
Provides-Extra: optimizers
Requires-Dist: ax-platform>=1.1.2; extra == "optimizers"
Requires-Dist: baybe>=0.14.0; extra == "optimizers"
Requires-Dist: nimo>=2.0.5; extra == "optimizers"
Provides-Extra: doc
Requires-Dist: sphinx; extra == "doc"
Requires-Dist: sphinx-rtd-theme; extra == "doc"
Requires-Dist: sphinxcontrib-httpdomain; extra == "doc"
Provides-Extra: dev
Requires-Dist: pytest; extra == "dev"
Dynamic: license-file
